batmouse/__init__.py
batmouse/__main__.py
batmouse/api.py
batmouse/convert_voltage.py
batmouse/mouse.py
batmouse/power_supply.py
batmouse/sys_power_supply.py
batmouse/table.py
batmouse-0.1.2.dist-info/WHEEL
batmouse-0.1.2.dist-info/METADATA
batmouse-0.1.2.dist-info/RECORD
